{
"type": "FeatureCollection",
"crs": { "type": "name", "properties": { "name": "urn:ogc:def:crs:OGC:1.3:CRS84" } },
"features": [
{ "type": "Feature", "properties": { "県名": "沖縄県", "スポット": "阿嘉大橋", "住所": "Japan, Okinawa, 阿嘉大橋", "lat": 26.1879944, "lon": 127.2856456 }, "geometry": { "type": "Point", "coordinates": [ 127.2856456, 26.1879944 ] } },
{ "type": "Feature", "properties": { "県名": "沖縄県", "スポット": "アザナムイ展望台", "住所": "57HV+PH, Geruma, Zamami, Shimajiri District, Okinawa 901-3312, Japan", "lat": 26.1783394, "lon": 127.2953469 }, "geometry": { "type": "Point", "coordinates": [ 127.2953469, 26.1783394 ] } },
{ "type": "Feature", "properties": { "県名": "沖縄県", "スポット": "高良家住宅", "住所": "82 Geruma, Zamami, Shimajiri District, Okinawa 901-3312, Japan", "lat": 26.1770634, "lon": 127.2929976 }, "geometry": { "type": "Point", "coordinates": [ 127.2929976, 26.1770634 ] } },
{ "type": "Feature", "properties": { "県名": "沖縄県", "スポット": "慶留間橋", "住所": "Japan, 〒901-3312 Okinawa, Geruma, 慶留間橋", "lat": 26.1753074, "lon": 127.2931372 }, "geometry": { "type": "Point", "coordinates": [ 127.2931372, 26.1753074 ] } },
{ "type": "Feature", "properties": { "県名": "沖縄県", "スポット": "御殿の木", "住所": "275 Aka, Zamami, Shimajiri District, Okinawa 901-3311, Japan", "lat": 26.1912707, "lon": 127.2818668 }, "geometry": { "type": "Point", "coordinates": [ 127.2818668, 26.1912707 ] } },
{ "type": "Feature", "properties": { "県名": "沖縄県", "スポット": "ヒズシビーチ", "住所": "157 Aka, Zamami, Shimajiri District, Okinawa 901-3311, Japan", "lat": 26.1897589, "lon": 127.276217 }, "geometry": { "type": "Point", "coordinates": [ 127.276217, 26.1897589 ] } },
{ "type": "Feature", "properties": { "県名": "沖縄県", "スポット": "天城展望台", "住所": "Aka, Zamami, Shimajiri District, Okinawa 901-3311, Japan", "lat": 26.1875202, "lon": 127.2766591 }, "geometry": { "type": "Point", "coordinates": [ 127.2766591, 26.1875202 ] } },
{ "type": "Feature", "properties": { "県名": "沖縄県", "スポット": "ニシバマビーチ", "住所": "Aka, Zamami, Shimajiri District, Okinawa 901-3311, Japan", "lat": 26.2019203, "lon": 127.2874334 }, "geometry": { "type": "Point", "coordinates": [ 127.2874334, 26.2019203 ] } }
]
}
